mcp_llms_txt/__init__.py
mcp_llms_txt/server.py
iflow_mcp_mcp_llms_txt-0.2.0.dist-info/METADATA
iflow_mcp_mcp_llms_txt-0.2.0.dist-info/WHEEL
iflow_mcp_mcp_llms_txt-0.2.0.dist-info/entry_points.txt
iflow_mcp_mcp_llms_txt-0.2.0.dist-info/licenses/LICENSE
iflow_mcp_mcp_llms_txt-0.2.0.dist-info/RECORD
