Metadata-Version: 2.4
Name: iflow-mcp_mcp-llms-txt
Version: 0.2.0
Summary: Add your description here
Author-email: TerminalMan <84923604+SecretiveShell@users.noreply.github.com>
License-File: LICENSE
Requires-Python: >=3.11
Requires-Dist: httpx>=0.28.1
Requires-Dist: mcp>=1.2.1
Requires-Dist: pydantic>=2.10.6
